rando_wisdom
